overture_to_arcgis/__init__.py
overture_to_arcgis/__main__.py
overture_to_arcgis/utils/__init__.py
overture_to_arcgis/utils/__main__.py
overture_to_arcgis/utils/_arcgis.py
overture_to_arcgis/utils/_logging.py
overture_to_arcgis-0.2.0.dev2.dist-info/licenses/LICENSE
overture_to_arcgis-0.2.0.dev2.dist-info/METADATA
overture_to_arcgis-0.2.0.dev2.dist-info/WHEEL
overture_to_arcgis-0.2.0.dev2.dist-info/top_level.txt
overture_to_arcgis-0.2.0.dev2.dist-info/RECORD
