Metadata-Version: 2.4
Name: overture-to-arcgis
Version: 0.2.0.dev2
Summary: Utility for easily getting data from Overture into ArcGIS Pro.
Author: Joel McCune (https://github.com/knu2xs)
License-Expression: Apache-2.0
Classifier: Programming Language :: Python :: 3
Requires-Python: >=3.9
License-File: LICENSE
Requires-Dist: arcgis>=2.2.0
Requires-Dist: geomet>=1.0.0
Requires-Dist: numpy>=1.7
Requires-Dist: pandas>=1.0.5
Requires-Dist: pyarrow>=1.0.0
Provides-Extra: h3
Requires-Dist: h3; extra == "h3"
Dynamic: license-file
